insomnia/__init__.py
insomnia/insomnia.css
insomnia/insomnia.py
insomnia/tui.py
insomnia_app-0.1.0.dist-info/entry_points.txt
insomnia_app-0.1.0.dist-info/LICENSE
insomnia_app-0.1.0.dist-info/WHEEL
insomnia_app-0.1.0.dist-info/METADATA
insomnia_app-0.1.0.dist-info/RECORD
