Metadata-Version: 2.1
Name: insomnia-app
Version: 0.1.0
Summary: A TUI app to find out why your computer stays awake at night
Home-page: https://github.com/davidfokkema/insomnia
Author: David Fokkema
Author-email: davidfokkema@icloud.com
Requires-Python: >=3.9,<4.0
Classifier: Development Status :: 4 - Beta
Classifier: Environment :: Console
Classifier: Intended Audience :: Developers
Classifier: Intended Audience :: End Users/Desktop
Classifier: Intended Audience :: System Administrators
Classifier: Operating System :: MacOS
Classifier: Operating System :: Microsoft :: Windows
Classifier: Operating System :: POSIX
Classifier: Programming Language :: Python
Classifier: Programming Language :: Python :: 3
Classifier: Programming Language :: Python :: 3.9
Classifier: Programming Language :: Python :: 3.10
Classifier: Programming Language :: Python :: 3.11
Requires-Dist: humanize (>=4.4.0,<5.0.0)
Requires-Dist: psutil (>=5.9.4,<6.0.0)
Requires-Dist: rich (>=13.0.0,<14.0.0)
Requires-Dist: textual (>=0.9.0,<0.10.0)
